{
"Hi":"*เทเทเถบเท เทเถธเถบเท เถเถบเทเถง เถเทเทเทเถธ เถฏ?๐ค๐ค*",
"Good Morning":"*Good Morning เทเถธเถบเท โบ๏ธ*",
"Good Night":"*Good Night.. เถถเถถเท เถถเทเถฏเทเทเถปเถซเถบเท Tc ๐คญ*",
"Bye":"*Bye bye Online เถเทเทเถธ massage เถเถเถเท เถฏเทเถฑเทเถฑ..๐*",
"Gm":"*Good Morning เทเถธเถบเท โบ๏ธ*",
"Gn":"*Good Night.. เถถเถถเท เถถเทเถฏเทเทเถปเถซเถบเท Tc ๐คญ*",
"owner":"*TECH SHAN๐ซ",
"Mk":"เถธเทเถเทเถญเท เถฑเท เถเถฑเท เถเถบเท เถธเทเถเถฏ เถเถปเถฑเทเถฑเท ๐๐",
"Mokad karanne":"เถธเทเถเทเถญเท เถฑเท เถเถฑเท เถเถบเท เถธเทเถเถฏ เถเถปเถฑเทเถฑเท ๐๐",
"mn":"*Hm hmmm..๐*",
"Hm":"*เถธเทเถเถฏ เทเทเถธเทเถธเท เถเทเถฑเทเถฑเท เถถเทเทเทเทเถเถฏ ๐ฉ๐*"
}
